{
  "generated_at": "2026-07-20T09:46:06+07:00",
  "data_as_of": "2026-07-20T00:00:00",
  "schema_version": "1.0",
  "cusi": {
    "value": 46.5,
    "level": "WATCH",
    "level_color": "#d29922",
    "level_emoji": "🟡",
    "change_1d": null,
    "as_of": "2026-07-20",
    "weights": {
      "jpy_momentum": 0.2,
      "audjpy_drawdown": 0.15,
      "spread_compression": 0.15,
      "vix": 0.15,
      "fx_realized_vol": 0.1,
      "cot_positioning": 0.1,
      "move": 0.05,
      "nikkei_momentum": 0.05,
      "mxnjpy_drawdown": 0.05
    },
    "components": {
      "cot_positioning": {
        "z": 1.392,
        "weight": 0.1,
        "contribution": 0.1392,
        "share_pct": 33.3
      },
      "mxnjpy_drawdown": {
        "z": 0.154,
        "weight": 0.05,
        "contribution": 0.0077,
        "share_pct": 1.8
      },
      "jpy_momentum": {
        "z": -0.092,
        "weight": 0.2,
        "contribution": -0.0184,
        "share_pct": 4.4
      },
      "fx_realized_vol": {
        "z": -1.139,
        "weight": 0.1,
        "contribution": -0.1139,
        "share_pct": 27.2
      },
      "audjpy_drawdown": {
        "z": -0.926,
        "weight": 0.15,
        "contribution": -0.139,
        "share_pct": 33.2
      }
    }
  },
  "indicators": {
    "usdjpy": {
      "last": 162.351,
      "chg_1d_pct": -0.02,
      "chg_5d_pct": 0.29,
      "z_5d": 0.09
    },
    "audjpy": {
      "last": 113.543,
      "chg_1d_pct": -0.07,
      "dd_from_20d_high_pct": -0.07
    },
    "jgb10y": {
      "last": 2.719,
      "chg_5d_bps": -14.7,
      "source": "MOF"
    },
    "us10y": {
      "last": 4.541,
      "chg_5d_bps": -2.8
    },
    "spread_us_jp": {
      "last": 1.822,
      "chg_20d_bps": 2.7,
      "z": -1.03
    },
    "vix": {
      "last": 18.77,
      "chg_5d": 3.74,
      "percentile_3y": 75.3
    },
    "move": {
      "last": 70.88
    },
    "fx_vol": {
      "realized_10d": 3.52,
      "atr_pct_14": 0.41,
      "vol_of_vol": 1.2,
      "percentile_3y": 7.4
    },
    "nikkei": {
      "last": 64141.12,
      "chg_5d_pct": -6.44
    },
    "mxnjpy": {
      "last": 9.241,
      "dd_from_20d_high_pct": -0.88
    },
    "cot_jpy": {
      "net_position": -122663,
      "noncomm_long": 115965,
      "noncomm_short": 238628,
      "z": -1.37,
      "report_date": "2026-07-14",
      "available_from": "2026-07-17"
    },
    "dxy": {
      "last": 100.74,
      "chg_5d_pct": -0.53
    },
    "gold": {
      "last": 4017.5,
      "chg_5d_pct": 0.51
    },
    "btc": {
      "last": 64823.97,
      "chg_5d_pct": -0.2
    },
    "ndx": {
      "last": 28592.66,
      "chg_5d_pct": -4.13
    },
    "spx": {
      "last": 7457.69,
      "chg_5d_pct": -1.55
    },
    "us2y": {
      "last": 3.997,
      "chg_5d_bps": 3.9
    }
  },
  "alerts": [],
  "data_quality": {
    "jgb_source": "MOF",
    "jgb_is_proxy": false,
    "missing": [],
    "stale": [
      "move",
      "ndx",
      "nikkei",
      "spx",
      "us10y",
      "us2y",
      "vix"
    ],
    "tickers_ok": 13,
    "tickers_total": 13,
    "indicator_rows": 1491
  }
}
